flask_cognito_lib/__init__.py
flask_cognito_lib/config.py
flask_cognito_lib/decorators.py
flask_cognito_lib/exceptions.py
flask_cognito_lib/plugin.py
flask_cognito_lib/py.typed
flask_cognito_lib/utils.py
flask_cognito_lib/services/__init__.py
flask_cognito_lib/services/cognito_svc.py
flask_cognito_lib/services/token_svc.py
flask_cognito_lib-1.9.6.dist-info/METADATA
flask_cognito_lib-1.9.6.dist-info/WHEEL
flask_cognito_lib-1.9.6.dist-info/licenses/LICENSE
flask_cognito_lib-1.9.6.dist-info/RECORD
