Metadata-Version: 2.4
Name: flask_cognito_lib
Version: 1.9.6
Summary: A Flask extension that supports protecting routes with AWS Cognito following OAuth 2.1 best practices
Project-URL: Homepage, https://github.com/mblackgeo/flask-cognito-lib
Project-URL: Repository, https://github.com/mblackgeo/flask-cognito-lib
Author-email: mblackgeo <18327836+mblackgeo@users.noreply.github.com>
License-Expression: MIT
License-File: LICENSE
Keywords: Cognito,Extension,Flask,OAuth
Classifier: Environment :: Web Environment
Classifier: Framework :: Flask
Classifier: Intended Audience :: Developers
Classifier: License :: OSI Approved :: MIT License
Classifier: Operating System :: OS Independent
Classifier: Programming Language :: Python :: 3
Classifier: Topic :: Internet :: WWW/HTTP :: Dynamic Content
Classifier: Topic :: Internet :: WWW/HTTP :: WSGI
Classifier: Topic :: Internet :: WWW/HTTP :: WSGI :: Middleware
Classifier: Topic :: Software Development :: Libraries :: Python Modules
Classifier: Typing :: Typed
Requires-Python: !=3.9.0,!=3.9.1,<4.0,>=3.9
Requires-Dist: cryptography
Requires-Dist: flask<4.0,>=2.0
Requires-Dist: pyjwt[crypto]<3.0,>=2.4
Requires-Dist: requests~=2.0
Requires-Dist: typing-extensions~=4.0
Requires-Dist: urllib3<3.0
Provides-Extra: build
Requires-Dist: uv~=0.7; extra == 'build'
